tello_binom.py
tello_binom-1.0.1.dist-info/METADATA
tello_binom-1.0.1.dist-info/WHEEL
tello_binom-1.0.1.dist-info/top_level.txt
tello_binom-1.0.1.dist-info/RECORD
