Metadata-Version: 2.1
Name: tello-binom
Version: 1.0.1
Summary: UNKNOWN
Home-page: UNKNOWN
Author: UNKNOWN
Author-email: UNKNOWN
License: UNKNOWN
Platform: UNKNOWN
Requires-Dist: opencv-python
Requires-Dist: pillow
Requires-Dist: pygame
